autosom/__init__.py
autosom/addition_annotator.py
autosom/autosom.py
autosom/base_annotator.py
autosom/complex_annotator.py
autosom/elimination_annotator.py
autosom/redox_annotator.py
autosom/utils.py
autosom-1.1.2.dist-info/METADATA
autosom-1.1.2.dist-info/WHEEL
autosom-1.1.2.dist-info/licenses/LICENSE
autosom-1.1.2.dist-info/RECORD
