Metadata-Version: 2.1
Name: autosom
Version: 1.1.2
Summary: Annotates the Sites of Metabolism (SOMs) of substrate-metabolite pairs.
Author-email: Roxane Jacob <roxane.axel.jacob@univie.ac.at>
License: MIT License
License-File: LICENSE
Requires-Python: >=3.11
Requires-Dist: chembl-structure-pipeline>=1.2.2
Requires-Dist: networkx>=3.3
Requires-Dist: numpy>=2.0.0
Requires-Dist: pandas>=2.2.3
Requires-Dist: rdkit>=2024.3.1
Requires-Dist: tqdm>=4.1.0
Provides-Extra: dev
Requires-Dist: black; extra == 'dev'
Requires-Dist: flake8; extra == 'dev'
Requires-Dist: isort; extra == 'dev'
Requires-Dist: mypy; extra == 'dev'
Requires-Dist: pydocstyle; extra == 'dev'
Requires-Dist: pytest; extra == 'dev'
Provides-Extra: vis
Requires-Dist: ipykernel; extra == 'vis'
Requires-Dist: ipywidgets; extra == 'vis'
